openflex/__init__.py
openflex/config.py
openflex/main.py
openflex/tcl/quartus_results.tcl
openflex/tcl/vivado_flow.tcl
openflex-0.1.4.dist-info/LICENSE
openflex-0.1.4.dist-info/METADATA
openflex-0.1.4.dist-info/WHEEL
openflex-0.1.4.dist-info/entry_points.txt
openflex-0.1.4.dist-info/top_level.txt
openflex-0.1.4.dist-info/RECORD
