Metadata-Version: 2.1
Name: openflex
Version: 0.1.4
Summary: Framework for Logic Synthesis and EXploration
Author: Greg Stitt, Wesley Piard
License: MIT License
Project-URL: Homepage, https://github.com/wespiard/openflex
Keywords: rtl,hdl,fpga
License-File: LICENSE
Requires-Dist: pyyaml>=6
Requires-Dist: click>=8
